setup.cfg
setup.py
smusher.py
d3smush.egg-info/PKG-INFO
d3smush.egg-info/SOURCES.txt
d3smush.egg-info/dependency_links.txt
d3smush.egg-info/entry_points.txt
d3smush.egg-info/requires.txt
d3smush.egg-info/top_level.txt