Metadata-Version: 1.1
Name: d3smush
Version: 0.1
Summary: Library to smush together D3 components in the right order
Home-page: https://github.com/xaranke/d3smush
Author: Kshitij Aranke
Author-email: kshitij.aranke@gmail.com
License: UNKNOWN
Download-URL: https://github.com/xaranke/d3smush/tarball/0.1
Keywords: d3,smush,javascript
Platform: UNKNOWN
